bittensor_cli/__init__.py
bittensor_cli/cli.py
bittensor_cli/doc_generation_helper.py
bittensor_cli/version.py
bittensor_cli/src/__init__.py
bittensor_cli/src/bittensor/__init__.py
bittensor_cli/src/bittensor/balances.py
bittensor_cli/src/bittensor/chain_data.py
bittensor_cli/src/bittensor/minigraph.py
bittensor_cli/src/bittensor/networking.py
bittensor_cli/src/bittensor/subtensor_interface.py
bittensor_cli/src/bittensor/utils.py
bittensor_cli/src/bittensor/extrinsics/__init__.py
bittensor_cli/src/bittensor/extrinsics/registration.py
bittensor_cli/src/bittensor/extrinsics/root.py
bittensor_cli/src/bittensor/extrinsics/transfer.py
bittensor_cli/src/bittensor/templates/main-filters.j2
bittensor_cli/src/bittensor/templates/main-header.j2
bittensor_cli/src/bittensor/templates/neuron-details.j2
bittensor_cli/src/bittensor/templates/price-multi.j2
bittensor_cli/src/bittensor/templates/price-single.j2
bittensor_cli/src/bittensor/templates/subnet-details-header.j2
bittensor_cli/src/bittensor/templates/subnet-details.j2
bittensor_cli/src/bittensor/templates/subnet-metrics.j2
bittensor_cli/src/bittensor/templates/subnets-table.j2
bittensor_cli/src/bittensor/templates/table.j2
bittensor_cli/src/bittensor/templates/view.css
bittensor_cli/src/bittensor/templates/view.j2
bittensor_cli/src/bittensor/templates/view.js
bittensor_cli/src/commands/__init__.py
bittensor_cli/src/commands/sudo.py
bittensor_cli/src/commands/view.py
bittensor_cli/src/commands/wallets.py
bittensor_cli/src/commands/weights.py
bittensor_cli/src/commands/liquidity/__init__.py
bittensor_cli/src/commands/liquidity/liquidity.py
bittensor_cli/src/commands/liquidity/utils.py
bittensor_cli/src/commands/stake/__init__.py
bittensor_cli/src/commands/stake/add.py
bittensor_cli/src/commands/stake/children_hotkeys.py
bittensor_cli/src/commands/stake/list.py
bittensor_cli/src/commands/stake/move.py
bittensor_cli/src/commands/stake/remove.py
bittensor_cli/src/commands/subnets/__init__.py
qbittensor-9.9.4.dist-info/METADATA
qbittensor-9.9.4.dist-info/WHEEL
qbittensor-9.9.4.dist-info/entry_points.txt
qbittensor-9.9.4.dist-info/top_level.txt
qbittensor-9.9.4.dist-info/RECORD
